kaleidoswap_sdk/__init__.py
kaleidoswap_sdk/client.py
kaleidoswap_sdk/exceptions.py
kaleidoswap_sdk/http.py
kaleidoswap_sdk/models.py
kaleidoswap_sdk/retry.py
kaleidoswap_sdk/websocket.py
kaleidoswap_sdk-0.1.5.dist-info/METADATA
kaleidoswap_sdk-0.1.5.dist-info/WHEEL
kaleidoswap_sdk-0.1.5.dist-info/RECORD
