Metadata-Version: 2.4
Name: kaleidoswap-sdk
Version: 0.1.5
Summary: Python SDK for KaleidoSwap - A decentralized exchange for Bitcoin and RGB assets
Project-URL: Homepage, https://github.com/kaleidoswap/kaleido-sdk
Project-URL: Documentation, https://github.com/kaleidoswap/kaleido-sdk#readme
Project-URL: Repository, https://github.com/kaleidoswap/kaleido-sdk.git
Project-URL: Issues, https://github.com/kaleidoswap/kaleido-sdk/issues
Author-email: Kaleidoswap Team <dev@kaleidoswap.com>
License: MIT
Keywords: bitcoin,crypto,dex,kaleidoswap,lightning-network,rgb,trading
Classifier: Development Status :: 3 - Alpha
Classifier: Intended Audience :: Developers
Classifier: License :: OSI Approved :: MIT License
Classifier: Programming Language :: Python :: 3
Classifier: Programming Language :: Python :: 3.11
Classifier: Programming Language :: Python :: 3.12
Requires-Python: >=3.11
Requires-Dist: aiohttp>=3.9.0
Requires-Dist: httpx>=0.27.0
Requires-Dist: pydantic>=2.0.0
Requires-Dist: websockets>=12.0
Provides-Extra: dev
Requires-Dist: black>=24.0.0; extra == 'dev'
Requires-Dist: mypy>=1.0.0; extra == 'dev'
Requires-Dist: pytest-asyncio>=0.24.0; extra == 'dev'
Requires-Dist: pytest-cov>=5.0.0; extra == 'dev'
Requires-Dist: pytest>=8.0.0; extra == 'dev'
Requires-Dist: ruff>=0.3.0; extra == 'dev'
